bgtrainer/LICENSE
bgtrainer/README
bgtrainer/main.py
bgtrainer-0.2.0.dist-info/METADATA
bgtrainer-0.2.0.dist-info/WHEEL
bgtrainer-0.2.0.dist-info/RECORD
