Metadata-Version: 2.4
Name: bgtrainer
Version: 0.2.0
Requires-Dist: pandas
